apd/__init__.py
apd/analysis_data.py
apd/ap_info.py
apd/authentication.py
apd/command.py
apd/data_cache.py
apd/eos.py
apd/pool_xml.py
apd/rich_console.py
apd/snakemake.py
apd-0.8.1.dist-info/LICENSE
apd-0.8.1.dist-info/METADATA
apd-0.8.1.dist-info/WHEEL
apd-0.8.1.dist-info/entry_points.txt
apd-0.8.1.dist-info/top_level.txt
apd-0.8.1.dist-info/RECORD
