Metadata-Version: 2.1
Name: apd
Version: 0.8.1
Summary: Tool to access the Analysis production Data
License: BSD-3-Clause
Classifier: License :: OSI Approved :: GNU General Public License v3 (GPLv3)
Classifier: Programming Language :: Python :: 3
Classifier: Programming Language :: Python :: 3.9
Classifier: Programming Language :: Python :: 3.10
Classifier: Programming Language :: Python :: 3.11
Requires-Python: >=3.9
License-File: LICENSE
Requires-Dist: requests
Requires-Dist: click
Requires-Dist: click-log
Requires-Dist: rich
Provides-Extra: testing
Requires-Dist: black; extra == "testing"
Requires-Dist: flake8; extra == "testing"
Requires-Dist: flake8-bugbear; extra == "testing"
Requires-Dist: pylint; extra == "testing"
Requires-Dist: pytest; extra == "testing"
Requires-Dist: pytest-cov; extra == "testing"
Requires-Dist: responses; extra == "testing"
